terrenos/__init__.py
terrenos/utils.py
terrenos/validation.py
terrenos/validations.py
terrenos-4.0.0.dist-info/METADATA
terrenos-4.0.0.dist-info/WHEEL
terrenos-4.0.0.dist-info/top_level.txt
terrenos-4.0.0.dist-info/RECORD
