Metadata-Version: 2.1
Name: terrenos
Version: 4.0.0
Summary: Paquete para trabajar con capas de terrenos y validar atributos
Home-page: https://github.com/tu_usuario/tu_repositorio
Author: dvanegasf
Author-email: tu_email@example.com
Classifier: Programming Language :: Python :: 3
Classifier: License :: OSI Approved :: MIT License
Classifier: Operating System :: OS Independent
Requires-Python: >=3.6
